trialML/__main__.py
trialML/power.py
trialML/theory.py
trialML/trial.py
trialML/tutorials/power_CIs.ipynb
trialML/tutorials/power_CIs.py
trialML/tutorials/real_data.py
trialML/tutorials/sensitivity.ipynb
trialML/tutorials/sensitivity.py
trialML/utils/__init__.py
trialML/utils/bootstrap.py
trialML/utils/m_classification.py
trialML/utils/stats.py
trialML/utils/theory.py
trialML/utils/utils.py
trialML/utils/vectorized.py
trialML-0.1.0.dist-info/LICENSE.txt
trialML-0.1.0.dist-info/METADATA
trialML-0.1.0.dist-info/WHEEL
trialML-0.1.0.dist-info/top_level.txt
trialML-0.1.0.dist-info/RECORD
