Metadata-Version: 2.1
Name: trialML
Version: 0.1.0
Summary: trialML package
Home-page: https://github.com/ErikinBC/trialML
Author: Erik Drysdale
Author-email: erikinwest@gmail.com
License: MIT
Platform: UNKNOWN
Classifier: Development Status :: 3 - Alpha
Classifier: Intended Audience :: Science/Research
Classifier: License :: OSI Approved :: MIT License
Classifier: Operating System :: POSIX :: Linux
Classifier: Programming Language :: Python :: 3
License-File: LICENSE.txt
Requires-Dist: numpy
Requires-Dist: pandas
